Workbook

Sheet Summary
B2: Dabur India FY26 - Budget vs Actual Summary
B3: Variance sign: F = favourable, U = Unfavourable
B5: Full year FY26 (₹ Cr) | C5: Budget | D5: Actual | E5: Variance | F5: Var % | G5: F / U
B6: Sales | C6: =Budget!G19 -> 13191.15 | D6: =Actuals!G6 -> 13193 | E6: =D6-C6 -> 1.85 | F6: =E6/C6 -> 0.00014024554 | G6: =IF(ROUND(F6,4)=0,"-",IF(F6>0,"F","U")) -> F
B7: Expenses | C7: =Budget!G20 -> 10759.014 | D7: =Actuals!G7 -> 10742 | E7: =C7-D7 -> 17.014 | F7: =E7/C7 -> 0.0015813717 | G7: =IF(ROUND(F7,4)=0,"-",IF(F7>0,"F","U")) -> F
B8: Operating profit | C8: =Budget!G21 -> 2432.136 | D8: =Actuals!G8 -> 2450 | E8: =D8-C8 -> 17.864 | F8: =E8/C8 -> 0.007344984 | G8: =IF(ROUND(F8,4)=0,"-",IF(F8>0,"F","U")) -> F
B9: Other income | C9: =Budget!G22 -> 578.55 | D9: =Actuals!G9 -> 585 | E9: =D9-C9 -> 6.45 | F9: =E9/C9 -> 0.011148561 | G9: =IF(ROUND(F9,4)=0,"-",IF(F9>0,"F","U")) -> F
B10: Interest | C10: =Budget!G23 -> 163 | D10: =Actuals!G10 -> 146 | E10: =C10-D10 -> 17 | F10: =E10/C10 -> 0.10429448 | G10: =IF(ROUND(F10,4)=0,"-",IF(F10>0,"F","U")) -> F
B11: Depreciation | C11: =Budget!G24 -> 446 | D11: =Actuals!G11 -> 468 | E11: =C11-D11 -> -22 | F11: =E11/C11 -> -0.049327354 | G11: =IF(ROUND(F11,4)=0,"-",IF(F11>0,"F","U")) -> U
B12: Profit before tax | C12: =Budget!G25 -> 2401.686 | D12: =Actuals!G12 -> 2421 | E12: =D12-C12 -> 19.314 | F12: =E12/C12 -> 0.0080418506 | G12: =IF(ROUND(F12,4)=0,"-",IF(F12>0,"F","U")) -> F
B13: Net profit | C13: =Budget!G27 -> 1846.0572 | D13: =Actuals!G14 -> 1869 | E13: =D13-C13 -> 22.94278 | F13: =E13/C13 -> 0.01242799 | G13: =IF(ROUND(F13,4)=0,"-",IF(F13>0,"F","U")) -> F
B14: Operating margin | C14: =C8/C6 -> 0.18437634 | D14: =D8/D6 -> 0.18570454 | E14: =(D14-C14)*10000 -> 13.281971
B16: Sales by quarter (₹ Cr) | C16: =Budget!C18 -> Jun-25 | D16: =Budget!D18 -> Sep-25 | E16: =Budget!E18 -> Dec-25 | F16: =Budget!F18 -> Mar-26
B17: Budget | C17: =Budget!C19 -> 3516.45 | D17: =Budget!D19 -> 3180.45 | E17: =Budget!E19 -> 3522.75 | F17: =Budget!F19 -> 2971.5
B18: Actual | C18: =Actuals!C6 -> 3405 | D18: =Actuals!D6 -> 3191 | E18: =Actuals!E6 -> 3559 | F18: =Actuals!F6 -> 3038
B19: Variance | C19: =C18-C17 -> -111.45 | D19: =D18-D17 -> 10.55 | E19: =E18-E17 -> 36.25 | F19: =F18-F17 -> 66.5
B20: Var % | C20: =C19/C17 -> -0.031693896 | D20: =D19/D17 -> 0.0033171407 | E20: =E19/E17 -> 0.010290256 | F20: =F19/F17 -> 0.02237927
B22: Key findings
B23: 1. Sales were on budget for the year: ₹13,193 Cr vs ₹13,191 Cr budget. But the path was uneven: Q1 missed budget by ₹111 Cr, and Q2-Q4 together came in ₹113 Cr above budget to make up the gap.
B24: 2. Costs were under control: ₹10,742 Cr vs ₹10,759 Cr budget (₹17 Cr under). Expenses stayed at 81.4% of sales vs 81.6% budgeted, despite rising input costs.
B25: 3. Operating profit beat budget by ₹18 Cr (+0.7%). Operating margin was 18.6% vs 18.4% budget (+13 bps).
B26: 4. Net profit beat budget by ₹23 Cr (+1.2%). Savings on interest (₹17 Cr) and extra other income (₹6 Cr) helped; depreciation ran ₹22 Cr over budget.
B27: 5. The sales line hid two opposite moves: volume was ₹81 Cr below budget (Q1 rains), while price/mix added ₹83 Cr. See Variance Drivers.
B28: 6. Cost lines vs budget (+ = saving, ₹ Cr): material +38, advertising +20, employee -20, other -20. Material savings paid for higher staff and overhead costs.
B30: Root causes
B31: 1. Bad weather: unseasonal rains in the summer quarter (Q1) hurt sales of drinks and other summer products.
B32: 2. GST change: a tax rate cut made distributors hold less stock in Q2, but demand picked up again from November.
B33: 3. Higher costs, balanced by price rises: raw materials got more expensive, but price increases, cost savings and strong sellers (hair oil, toothpaste, foods, online sales) kept profits on track.
B35: Recommendations - what to do next
... B38: 3. Budget the smaller lines properly: base interest, depreciation and other income on actual plans and current rates, not last year's numbers.

Sheet Budget
B2: FY26 budget (Built from FY25 actuals)
B4: FY25 Actuals
B5: ₹ Cr | C5: Jun-24 | D5: Sep-24 | E5: Dec-24 | F5: Mar-25 | G5: FY25 Total
B6: Sales | C6: {=_xlfn.XLOOKUP($B6,Data!$B$4:$B$13,_xlfn.XLOOKUP(C$5,Data!$C$3:$N$3,Data!$C$4:$N$13))} -> 3349 | D6: {=_xlfn.XLOOKUP($B6,Data!$B$4:$B$13,_xlfn.XLOOKUP(D$5,Data!$C$3:$N$3,Data!$C$4:$N$13))} -> 3029 | E6: {=_xlfn.XLOOKUP($B6,Data!$B$4:$B$13,_xlfn.XLOOKUP(E$5,Data!$C$3:$N$3,Data!$C$4:$N$13))} -> 3355 | F6: {=_xlfn.XLOOKUP($B6,Data!$B$4:$B$13,_xlfn.XLOOKUP(F$5,Data!$C$3:$N$3,Data!$C$4:$N$13))} -> 2830 | G6: =SUM(C6:F6) -> 12563
B7: Expenses | C7: {=_xlfn.XLOOKUP($B7,Data!$B$4:$B$13,_xlfn.XLOOKUP(C$5,Data!$C$3:$N$3,Data!$C$4:$N$13))} -> 2694 | D7: {=_xlfn.XLOOKUP($B7,Data!$B$4:$B$13,_xlfn.XLOOKUP(D$5,Data!$C$3:$N$3,Data!$C$4:$N$13))} -> 2476 | E7: {=_xlfn.XLOOKUP($B7,Data!$B$4:$B$13,_xlfn.XLOOKUP(E$5,Data!$C$3:$N$3,Data!$C$4:$N$13))} -> 2673 | F7: {=_xlfn.XLOOKUP($B7,Data!$B$4:$B$13,_xlfn.XLOOKUP(F$5,Data!$C$3:$N$3,Data!$C$4:$N$13))} -> 2403 | G7: =SUM(C7:F7) -> 10246
B8: Operating Profit | C8: {=_xlfn.XLOOKUP($B8,Data!$B$4:$B$13,_xlfn.XLOOKUP(C$5,Data!$C$3:$N$3,Data!$C$4:$N$13))} -> 655 | D8: {=_xlfn.XLOOKUP($B8,Data!$B$4:$B$13,_xlfn.XLOOKUP(D$5,Data!$C$3:$N$3,Data!$C$4:$N$13))} -> 553 | E8: {=_xlfn.XLOOKUP($B8,Data!$B$4:$B$13,_xlfn.XLOOKUP(E$5,Data!$C$3:$N$3,Data!$C$4:$N$13))} -> 682 | F8: {=_xlfn.XLOOKUP($B8,Data!$B$4:$B$13,_xlfn.XLOOKUP(F$5,Data!$C$3:$N$3,Data!$C$4:$N$13))} -> 427 | G8: =G6-G7 -> 2317
B9: Other Income | C9: {=_xlfn.XLOOKUP($B9,Data!$B$4:$B$13,_xlfn.XLOOKUP(C$5,Data!$C$3:$N$3,Data!$C$4:$N$13))} -> 129 | D9: {=_xlfn.XLOOKUP($B9,Data!$B$4:$B$13,_xlfn.XLOOKUP(D$5,Data!$C$3:$N$3,Data!$C$4:$N$13))} -> 152 | E9: {=_xlfn.XLOOKUP($B9,Data!$B$4:$B$13,_xlfn.XLOOKUP(E$5,Data!$C$3:$N$3,Data!$C$4:$N$13))} -> 129 | F9: {=_xlfn.XLOOKUP($B9,Data!$B$4:$B$13,_xlfn.XLOOKUP(F$5,Data!$C$3:$N$3,Data!$C$4:$N$13))} -> 141 | G9: =SUM(C9:F9) -> 551
B10: Interest | C10: {=_xlfn.XLOOKUP($B10,Data!$B$4:$B$13,_xlfn.XLOOKUP(C$5,Data!$C$3:$N$3,Data!$C$4:$N$13))} -> 33 | D10: {=_xlfn.XLOOKUP($B10,Data!$B$4:$B$13,_xlfn.XLOOKUP(D$5,Data!$C$3:$N$3,Data!$C$4:$N$13))} -> 47 | E10: {=_xlfn.XLOOKUP($B10,Data!$B$4:$B$13,_xlfn.XLOOKUP(E$5,Data!$C$3:$N$3,Data!$C$4:$N$13))} -> 44 | F10: {=_xlfn.XLOOKUP($B10,Data!$B$4:$B$13,_xlfn.XLOOKUP(F$5,Data!$C$3:$N$3,Data!$C$4:$N$13))} -> 39 | G10: =SUM(C10:F10) -> 163
B11: Depreciation | C11: {=_xlfn.XLOOKUP($B11,Data!$B$4:$B$13,_xlfn.XLOOKUP(C$5,Data!$C$3:$N$3,Data!$C$4:$N$13))} -> 109 | D11: {=_xlfn.XLOOKUP($B11,Data!$B$4:$B$13,_xlfn.XLOOKUP(D$5,Data!$C$3:$N$3,Data!$C$4:$N$13))} -> 111 | E11: {=_xlfn.XLOOKUP($B11,Data!$B$4:$B$13,_xlfn.XLOOKUP(E$5,Data!$C$3:$N$3,Data!$C$4:$N$13))} -> 109 | F11: {=_xlfn.XLOOKUP($B11,Data!$B$4:$B$13,_xlfn.XLOOKUP(F$5,Data!$C$3:$N$3,Data!$C$4:$N$13))} -> 117 | G11: =SUM(C11:F11) -> 446
B12: Profit before tax | C12: {=_xlfn.XLOOKUP($B12,Data!$B$4:$B$13,_xlfn.XLOOKUP(C$5,Data!$C$3:$N$3,Data!$C$4:$N$13))} -> 642 | D12: {=_xlfn.XLOOKUP($B12,Data!$B$4:$B$13,_xlfn.XLOOKUP(D$5,Data!$C$3:$N$3,Data!$C$4:$N$13))} -> 546 | E12: {=_xlfn.XLOOKUP($B12,Data!$B$4:$B$13,_xlfn.XLOOKUP(E$5,Data!$C$3:$N$3,Data!$C$4:$N$13))} -> 658 | F12: {=_xlfn.XLOOKUP($B12,Data!$B$4:$B$13,_xlfn.XLOOKUP(F$5,Data!$C$3:$N$3,Data!$C$4:$N$13))} -> 412 | G12: =G8+G9-G10-G11 -> 2259
B13: Tax % | C13: {=_xlfn.XLOOKUP($B13,Data!$B$4:$B$13,_xlfn.XLOOKUP(C$5,Data!$C$3:$N$3,Data!$C$4:$N$13))} -> 0.23 | D13: {=_xlfn.XLOOKUP($B13,Data!$B$4:$B$13,_xlfn.XLOOKUP(D$5,Data!$C$3:$N$3,Data!$C$4:$N$13))} -> 0.24 | E13: {=_xlfn.XLOOKUP($B13,Data!$B$4:$B$13,_xlfn.XLOOKUP(E$5,Data!$C$3:$N$3,Data!$C$4:$N$13))} -> 0.22 | F13: {=_xlfn.XLOOKUP($B13,Data!$B$4:$B$13,_xlfn.XLOOKUP(F$5,Data!$C$3:$N$3,Data!$C$4:$N$13))} -> 0.24 | G13: =1-G14/G12 -> 0.229305
B14: Net Profit | C14: {=_xlfn.XLOOKUP($B14,Data!$B$4:$B$13,_xlfn.XLOOKUP(C$5,Data!$C$3:$N$3,Data!$C$4:$N$13))} -> 494 | D14: {=_xlfn.XLOOKUP($B14,Data!$B$4:$B$13,_xlfn.XLOOKUP(D$5,Data!$C$3:$N$3,Data!$C$4:$N$13))} -> 418 | E14: {=_xlfn.XLOOKUP($B14,Data!$B$4:$B$13,_xlfn.XLOOKUP(E$5,Data!$C$3:$N$3,Data!$C$4:$N$13))} -> 516 | F14: {=_xlfn.XLOOKUP($B14,Data!$B$4:$B$13,_xlfn.XLOOKUP(F$5,Data!$C$3:$N$3,Data!$C$4:$N$13))} -> 313 | G14: =SUM(C14:F14) -> 1741
B17: FY26 Budget | I17: Year to Date
B18: ₹ Cr | C18: Jun-25 | D18: Sep-25 | E18: Dec-25 | F18: Mar-26 | G18: FY26 Total | I18: ₹ Cr | J18: Jun-25 | K18: Sep-25 | L18: Dec-25 | M18: Mar-26
B19: Sales | C19: =C6*(1+$C$40) -> 3516.45 | D19: =D6*(1+$C$40) -> 3180.45 | E19: =E6*(1+$C$40) -> 3522.75 | F19: =F6*(1+$C$40) -> 2971.5 | G19: =SUM(C19:F19) -> 13191.15 | I19: =B19 -> Sales | J19: =SUM($C19:C19) -> 3516.45 | K19: =SUM($C19:D19) -> 6696.9 | L19: =SUM($C19:E19) -> 10219.65 | M19: =SUM($C19:F19) -> 13191.15
B20: Expenses | C20: =C37 -> 2828.784 | D20: =D37 -> 2599.8 | E20: =E37 -> 2806.965 | F20: =F37 -> 2523.465 | G20: =SUM(C20:F20) -> 10759.014 | I20: =B20 -> Expenses | J20: =SUM($C20:C20) -> 2828.784 | K20: =SUM($C20:D20) -> 5428.584 | L20: =SUM($C20:E20) -> 8235.549 | M20: =SUM($C20:F20) -> 10759.014
B21: Operating Profit | C21: =C19-C20 -> 687.666 | D21: =D19-D20 -> 580.65 | E21: =E19-E20 -> 715.785 | F21: =F19-F20 -> 448.035 | G21: =G19-G20 -> 2432.136 | I21: =B21 -> Operating Profit | J21: =SUM($C21:C21) -> 687.666 | K21: =SUM($C21:D21) -> 1268.316 | L21: =SUM($C21:E21) -> 1984.101 | M21: =SUM($C21:F21) -> 2432.136
B22: Other Income | C22: =C9*(1+$C$41) -> 135.45 | D22: =D9*(1+$C$41) -> 159.6 | E22: =E9*(1+$C$41) -> 135.45 | F22: =F9*(1+$C$41) -> 148.05 | G22: =SUM(C22:F22) -> 578.55 | I22: =B22 -> Other Income | J22: =SUM($C22:C22) -> 135.45 | K22: =SUM($C22:D22) -> 295.05 | L22: =SUM($C22:E22) -> 430.5 | M22: =SUM($C22:F22) -> 578.55
B23: Interest | C23: =C10 -> 33 | D23: =D10 -> 47 | E23: =E10 -> 44 | F23: =F10 -> 39 | G23: =SUM(C23:F23) -> 163 | I23: =B23 -> Interest | J23: =SUM($C23:C23) -> 33 | K23: =SUM($C23:D23) -> 80 | L23: =SUM($C23:E23) -> 124 | M23: =SUM($C23:F23) -> 163
B24: Depreciation | C24: =C11 -> 109 | D24: =D11 -> 111 | E24: =E11 -> 109 | F24: =F11 -> 117 | G24: =SUM(C24:F24) -> 446 | I24: =B24 -> Depreciation | J24: =SUM($C24:C24) -> 109 | K24: =SUM($C24:D24) -> 220 | L24: =SUM($C24:E24) -> 329 | M24: =SUM($C24:F24) -> 446
B25: Profit before tax | C25: =C21+C22-C23-C24 -> 681.116 | D25: =D21+D22-D23-D24 -> 582.25 | E25: =E21+E22-E23-E24 -> 698.235 | F25: =F21+F22-F23-F24 -> 440.085 | G25: =G21+G22-G23-G24 -> 2401.686 | I25: =B25 -> Profit before tax | J25: =SUM($C25:C25) -> 681.116 | K25: =SUM($C25:D25) -> 1263.366 | L25: =SUM($C25:E25) -> 1961.601 | M25: =SUM($C25:F25) -> 2401.686
B26: Tax % | C26: =C13 -> 0.23 | D26: =D13 -> 0.24 | E26: =E13 -> 0.22 | F26: =F13 -> 0.24 | G26: =1-G27/G25 -> 0.23134947 | I26: =B26 -> Tax % | J26: =1-J27/J25 -> 0.23 | K26: =1-K27/K25 -> 0.23460872 | L26: =1-L27/L25 -> 0.22940872 | M26: =1-M27/M25 -> 0.23134947
B27: Net Profit | C27: =C25*(1-C26) -> 524.45932 | D27: =D25*(1-D26) -> 442.51 | E27: =E25*(1-E26) -> 544.6233 | F27: =F25*(1-F26) -> 334.4646 | G27: =SUM(C27:F27) -> 1846.0572 | I27: =B27 -> Net Profit | J27: =SUM($C27:C27) -> 524.45932 | K27: =SUM($C27:D27) -> 966.96932 | L27: =SUM($C27:E27) -> 1511.5926 | M27: =SUM($C27:F27) -> 1846.0572
B29: Cost breakdown
B31: FY26 Budget | I31: Year to Date
B32: ₹ Cr | C32: Jun-25 | D32: Sep-25 | E32: Dec-25 | F32: Mar-26 | G32: FY26 Total | I32: ₹ Cr | J32: Jun-25 | K32: Sep-25 | L32: Dec-25 | M32: Mar-26
B33: Material cost | C33: =C$19*(Data!G16/Data!G$4) -> 1836.0825 | D33: =D$19*(Data!H16/Data!H$4) -> 1611.015 | E33: =E$19*(Data!I16/Data!I$4) -> 1829.94 | F33: =F$19*(Data!J16/Data!J$4) -> 1584.555 | G33: =SUM(C33:F33) -> 6861.5925 | I33: =B33 -> Material cost | J33: =SUM($C33:C33) -> 1836.0825 | K33: =SUM($C33:D33) -> 3447.0975 | L33: =SUM($C33:E33) -> 5277.0375 | M33: =SUM($C33:F33) -> 6861.5925
B34: Employee cost | C34: =C$19*(Data!G17/Data!G$4) -> 339.066 | D34: =D$19*(Data!H17/Data!H$4) -> 355.74 | E34: =E$19*(Data!I17/Data!I$4) -> 351.96 | F34: =F$19*(Data!J17/Data!J$4) -> 309.12 | G34: =SUM(C34:F34) -> 1355.886 | I34: =B34 -> Employee cost | J34: =SUM($C34:C34) -> 339.066 | K34: =SUM($C34:D34) -> 694.806 | L34: =SUM($C34:E34) -> 1046.766 | M34: =SUM($C34:F34) -> 1355.886
B35: Advertisement & publicity | C35: =C$19*(Data!G18/Data!G$4) -> 247.6845 | D35: =D$19*(Data!H18/Data!H$4) -> 236.88 | E35: =E$19*(Data!I18/Data!I$4) -> 238.035 | F35: =F$19*(Data!J18/Data!J$4) -> 185.22 | G35: =SUM(C35:F35) -> 907.8195 | I35: =B35 -> Advertisement & publicity | J35: =SUM($C35:C35) -> 247.6845 | K35: =SUM($C35:D35) -> 484.5645 | L35: =SUM($C35:E35) -> 722.5995 | M35: =SUM($C35:F35) -> 907.8195
B36: Other expenses | C36: =C$19*(Data!G19/Data!G$4) -> 405.951 | D36: =D$19*(Data!H19/Data!H$4) -> 396.165 | E36: =E$19*(Data!I19/Data!I$4) -> 387.03 | F36: =F$19*(Data!J19/Data!J$4) -> 444.57 | G36: =SUM(C36:F36) -> 1633.716 | I36: =B36 -> Other expenses | J36: =SUM($C36:C36) -> 405.951 | K36: =SUM($C36:D36) -> 802.116 | L36: =SUM($C36:E36) -> 1189.146 | M36: =SUM($C36:F36) -> 1633.716
B37: Total expenses | C37: =SUM(C33:C36) -> 2828.784 | D37: =SUM(D33:D36) -> 2599.8 | E37: =SUM(E33:E36) -> 2806.965 | F37: =SUM(F33:F36) -> 2523.465 | G37: =SUM(G33:G36) -> 10759.014 | I37: =B37 -> Total expenses | J37: =SUM(J33:J36) -> 2828.784 | K37: =SUM(K33:K36) -> 5428.584 | L37: =SUM(L33:L36) -> 8235.549 | M37: =SUM(M33:M36) -> 10759.014
B39: Assumptions
B40: Sales growth | C40: 0.05 | D40: FY25 sales grew 1.3%; FY26 assumes recovery to 5%
B41: Other income growth | C41: 0.05 | D41: Modest growth on treasury income
B42: Cost lines | D42: Each cost line = budget sales × that line's % of sales in the same FY25 quarter.
B43: Net profit basis | D43: Budget net profit = PBT × (1 − tax rate). Actual net profit is the reported figure, which also reflects minority interest , a ₹2-4 Cr a quarter gap shown as "Tax & minority" in the bridge.
B44: Volume growth (within sales growth) | C44: 0.03 | D44: Assumed split of the 5% sales growth: 3% volume, rest price/mix. Used only for the volume vs price/mix analysis.
B45: Implied price/mix growth | C45: =(1+C40)/(1+C44)-1 -> 0.019417476 | D45: Worked out from sales growth and volume growth.

Sheet Actuals
B2: FY26 actuals (pulled from Data sheet)
B4: FY26 Actuals | I4: Year to Date
B5: ₹ Cr | C5: Jun-25 | D5: Sep-25 | E5: Dec-25 | F5: Mar-26 | G5: FY26 Total | I5: ₹ Cr | J5: Jun-25 | K5: Sep-25 | L5: Dec-25 | M5: Mar-26
B6: Sales | C6: =INDEX(Data!$B$3:$N$13,MATCH($B6,Data!$B$3:$B$13,0),MATCH(C$5,Data!$B$3:$N$3,0)) -> 3405 | D6: =INDEX(Data!$B$3:$N$13,MATCH($B6,Data!$B$3:$B$13,0),MATCH(D$5,Data!$B$3:$N$3,0)) -> 3191 | E6: =INDEX(Data!$B$3:$N$13,MATCH($B6,Data!$B$3:$B$13,0),MATCH(E$5,Data!$B$3:$N$3,0)) -> 3559 | F6: =INDEX(Data!$B$3:$N$13,MATCH($B6,Data!$B$3:$B$13,0),MATCH(F$5,Data!$B$3:$N$3,0)) -> 3038 | G6: =SUM(C6:F6) -> 13193 | I6: =B6 -> Sales | J6: =SUM($C6:C6) -> 3405 | K6: =SUM($C6:D6) -> 6596 | L6: =SUM($C6:E6) -> 10155 | M6: =SUM($C6:F6) -> 13193
B7: Expenses | C7: =INDEX(Data!$B$3:$N$13,MATCH($B7,Data!$B$3:$B$13,0),MATCH(C$5,Data!$B$3:$N$3,0)) -> 2737 | D7: =INDEX(Data!$B$3:$N$13,MATCH($B7,Data!$B$3:$B$13,0),MATCH(D$5,Data!$B$3:$N$3,0)) -> 2603 | E7: =INDEX(Data!$B$3:$N$13,MATCH($B7,Data!$B$3:$B$13,0),MATCH(E$5,Data!$B$3:$N$3,0)) -> 2825 | F7: =INDEX(Data!$B$3:$N$13,MATCH($B7,Data!$B$3:$B$13,0),MATCH(F$5,Data!$B$3:$N$3,0)) -> 2577 | G7: =SUM(C7:F7) -> 10742 | I7: =B7 -> Expenses | J7: =SUM($C7:C7) -> 2737 | K7: =SUM($C7:D7) -> 5340 | L7: =SUM($C7:E7) -> 8165 | M7: =SUM($C7:F7) -> 10742
B8: Operating Profit | C8: =INDEX(Data!$B$3:$N$13,MATCH($B8,Data!$B$3:$B$13,0),MATCH(C$5,Data!$B$3:$N$3,0)) -> 667 | D8: =INDEX(Data!$B$3:$N$13,MATCH($B8,Data!$B$3:$B$13,0),MATCH(D$5,Data!$B$3:$N$3,0)) -> 588 | E8: =INDEX(Data!$B$3:$N$13,MATCH($B8,Data!$B$3:$B$13,0),MATCH(E$5,Data!$B$3:$N$3,0)) -> 734 | F8: =INDEX(Data!$B$3:$N$13,MATCH($B8,Data!$B$3:$B$13,0),MATCH(F$5,Data!$B$3:$N$3,0)) -> 461 | G8: =SUM(C8:F8) -> 2450 | I8: =B8 -> Operating Profit | J8: =SUM($C8:C8) -> 667 | K8: =SUM($C8:D8) -> 1255 | L8: =SUM($C8:E8) -> 1989 | M8: =SUM($C8:F8) -> 2450
B9: Other Income | C9: =INDEX(Data!$B$3:$N$13,MATCH($B9,Data!$B$3:$B$13,0),MATCH(C$5,Data!$B$3:$N$3,0)) -> 144 | D9: =INDEX(Data!$B$3:$N$13,MATCH($B9,Data!$B$3:$B$13,0),MATCH(D$5,Data!$B$3:$N$3,0)) -> 140 | E9: =INDEX(Data!$B$3:$N$13,MATCH($B9,Data!$B$3:$B$13,0),MATCH(E$5,Data!$B$3:$N$3,0)) -> 126 | F9: =INDEX(Data!$B$3:$N$13,MATCH($B9,Data!$B$3:$B$13,0),MATCH(F$5,Data!$B$3:$N$3,0)) -> 175 | G9: =SUM(C9:F9) -> 585 | I9: =B9 -> Other Income | J9: =SUM($C9:C9) -> 144 | K9: =SUM($C9:D9) -> 284 | L9: =SUM($C9:E9) -> 410 | M9: =SUM($C9:F9) -> 585
B10: Interest | C10: =INDEX(Data!$B$3:$N$13,MATCH($B10,Data!$B$3:$B$13,0),MATCH(C$5,Data!$B$3:$N$3,0)) -> 35 | D10: =INDEX(Data!$B$3:$N$13,MATCH($B10,Data!$B$3:$B$13,0),MATCH(D$5,Data!$B$3:$N$3,0)) -> 40 | E10: =INDEX(Data!$B$3:$N$13,MATCH($B10,Data!$B$3:$B$13,0),MATCH(E$5,Data!$B$3:$N$3,0)) -> 31 | F10: =INDEX(Data!$B$3:$N$13,MATCH($B10,Data!$B$3:$B$13,0),MATCH(F$5,Data!$B$3:$N$3,0)) -> 40 | G10: =SUM(C10:F10) -> 146 | I10: =B10 -> Interest | J10: =SUM($C10:C10) -> 35 | K10: =SUM($C10:D10) -> 75 | L10: =SUM($C10:E10) -> 106 | M10: =SUM($C10:F10) -> 146
B11: Depreciation | C11: =INDEX(Data!$B$3:$N$13,MATCH($B11,Data!$B$3:$B$13,0),MATCH(C$5,Data!$B$3:$N$3,0)) -> 114 | D11: =INDEX(Data!$B$3:$N$13,MATCH($B11,Data!$B$3:$B$13,0),MATCH(D$5,Data!$B$3:$N$3,0)) -> 115 | E11: =INDEX(Data!$B$3:$N$13,MATCH($B11,Data!$B$3:$B$13,0),MATCH(E$5,Data!$B$3:$N$3,0)) -> 117 | F11: =INDEX(Data!$B$3:$N$13,MATCH($B11,Data!$B$3:$B$13,0),MATCH(F$5,Data!$B$3:$N$3,0)) -> 122 | G11: =SUM(C11:F11) -> 468 | I11: =B11 -> Depreciation | J11: =SUM($C11:C11) -> 114 | K11: =SUM($C11:D11) -> 229 | L11: =SUM($C11:E11) -> 346 | M11: =SUM($C11:F11) -> 468
B12: Profit before tax | C12: =INDEX(Data!$B$3:$N$13,MATCH($B12,Data!$B$3:$B$13,0),MATCH(C$5,Data!$B$3:$N$3,0)) -> 663 | D12: =INDEX(Data!$B$3:$N$13,MATCH($B12,Data!$B$3:$B$13,0),MATCH(D$5,Data!$B$3:$N$3,0)) -> 573 | E12: =INDEX(Data!$B$3:$N$13,MATCH($B12,Data!$B$3:$B$13,0),MATCH(E$5,Data!$B$3:$N$3,0)) -> 711 | F12: =INDEX(Data!$B$3:$N$13,MATCH($B12,Data!$B$3:$B$13,0),MATCH(F$5,Data!$B$3:$N$3,0)) -> 474 | G12: =SUM(C12:F12) -> 2421 | I12: =B12 -> Profit before tax | J12: =SUM($C12:C12) -> 663 | K12: =SUM($C12:D12) -> 1236 | L12: =SUM($C12:E12) -> 1947 | M12: =SUM($C12:F12) -> 2421
B13: Tax % | C13: =INDEX(Data!$B$3:$N$13,MATCH($B13,Data!$B$3:$B$13,0),MATCH(C$5,Data!$B$3:$N$3,0)) -> 0.23 | D13: =INDEX(Data!$B$3:$N$13,MATCH($B13,Data!$B$3:$B$13,0),MATCH(D$5,Data!$B$3:$N$3,0)) -> 0.22 | E13: =INDEX(Data!$B$3:$N$13,MATCH($B13,Data!$B$3:$B$13,0),MATCH(E$5,Data!$B$3:$N$3,0)) -> 0.22 | F13: =INDEX(Data!$B$3:$N$13,MATCH($B13,Data!$B$3:$B$13,0),MATCH(F$5,Data!$B$3:$N$3,0)) -> 0.24 | G13: =1-G14/G12 -> 0.22800496 | I13: =B13 -> Tax % | J13: =1-J14/J12 -> 0.23378582 | K13: =1-K14/K12 -> 0.2289644 | L13: =1-L14/L12 -> 0.2259887 | M13: =1-M14/M12 -> 0.22800496
B14: Net Profit | C14: =INDEX(Data!$B$3:$N$13,MATCH($B14,Data!$B$3:$B$13,0),MATCH(C$5,Data!$B$3:$N$3,0)) -> 508 | D14: =INDEX(Data!$B$3:$N$13,MATCH($B14,Data!$B$3:$B$13,0),MATCH(D$5,Data!$B$3:$N$3,0)) -> 445 | E14: =INDEX(Data!$B$3:$N$13,MATCH($B14,Data!$B$3:$B$13,0),MATCH(E$5,Data!$B$3:$N$3,0)) -> 554 | F14: =INDEX(Data!$B$3:$N$13,MATCH($B14,Data!$B$3:$B$13,0),MATCH(F$5,Data!$B$3:$N$3,0)) -> 362 | G14: =SUM(C14:F14) -> 1869 | I14: =B14 -> Net Profit | J14: =SUM($C14:C14) -> 508 | K14: =SUM($C14:D14) -> 953 | L14: =SUM($C14:E14) -> 1507 | M14: =SUM($C14:F14) -> 1869
B16: Cost breakdown
B18: FY26 Budget | I18: Year to Date
B19: ₹ Cr | C19: =C5 -> Jun-25 | D19: =D5 -> Sep-25 | E19: =E5 -> Dec-25 | F19: =F5 -> Mar-26 | G19: FY26 Total | I19: ₹ Cr | J19: =J5 -> Jun-25 | K19: =K5 -> Sep-25 | L19: =L5 -> Dec-25 | M19: =M5 -> Mar-26
B20: Material cost | C20: =INDEX(Data!$B$1:$N$20,MATCH($B20,Data!$B$1:$B$20,0),MATCH(C$5,Data!$B$3:$N$3,0)) -> 1803.3 | D20: =INDEX(Data!$B$1:$N$20,MATCH($B20,Data!$B$1:$B$20,0),MATCH(D$5,Data!$B$3:$N$3,0)) -> 1613.5 | E20: =INDEX(Data!$B$1:$N$20,MATCH($B20,Data!$B$1:$B$20,0),MATCH(E$5,Data!$B$3:$N$3,0)) -> 1836.9 | F20: =INDEX(Data!$B$1:$N$20,MATCH($B20,Data!$B$1:$B$20,0),MATCH(F$5,Data!$B$3:$N$3,0)) -> 1570.1 | G20: =SUM(C20:F20) -> 6823.8 | I20: =B20 -> Material cost | J20: =SUM($C20:C20) -> 1803.3 | K20: =SUM($C20:D20) -> 3416.8 | L20: =SUM($C20:E20) -> 5253.7 | M20: =SUM($C20:F20) -> 6823.8
B21: Employee cost | C21: =INDEX(Data!$B$1:$N$20,MATCH($B21,Data!$B$1:$B$20,0),MATCH(C$5,Data!$B$3:$N$3,0)) -> 337.8 | D21: =INDEX(Data!$B$1:$N$20,MATCH($B21,Data!$B$1:$B$20,0),MATCH(D$5,Data!$B$3:$N$3,0)) -> 347.9 | E21: =INDEX(Data!$B$1:$N$20,MATCH($B21,Data!$B$1:$B$20,0),MATCH(E$5,Data!$B$3:$N$3,0)) -> 351.8 | F21: =INDEX(Data!$B$1:$N$20,MATCH($B21,Data!$B$1:$B$20,0),MATCH(F$5,Data!$B$3:$N$3,0)) -> 338.2 | G21: =SUM(C21:F21) -> 1375.7 | I21: =B21 -> Employee cost | J21: =SUM($C21:C21) -> 337.8 | K21: =SUM($C21:D21) -> 685.7 | L21: =SUM($C21:E21) -> 1037.5 | M21: =SUM($C21:F21) -> 1375.7
B22: Advertisement & publicity | C22: =INDEX(Data!$B$1:$N$20,MATCH($B22,Data!$B$1:$B$20,0),MATCH(C$5,Data!$B$3:$N$3,0)) -> 202 | D22: =INDEX(Data!$B$1:$N$20,MATCH($B22,Data!$B$1:$B$20,0),MATCH(D$5,Data!$B$3:$N$3,0)) -> 233.6 | E22: =INDEX(Data!$B$1:$N$20,MATCH($B22,Data!$B$1:$B$20,0),MATCH(E$5,Data!$B$3:$N$3,0)) -> 238 | F22: =INDEX(Data!$B$1:$N$20,MATCH($B22,Data!$B$1:$B$20,0),MATCH(F$5,Data!$B$3:$N$3,0)) -> 214.5 | G22: =SUM(C22:F22) -> 888.1 | I22: =B22 -> Advertisement & publicity | J22: =SUM($C22:C22) -> 202 | K22: =SUM($C22:D22) -> 435.6 | L22: =SUM($C22:E22) -> 673.6 | M22: =SUM($C22:F22) -> 888.1
B23: Other expenses | C23: =INDEX(Data!$B$1:$N$20,MATCH($B23,Data!$B$1:$B$20,0),MATCH(C$5,Data!$B$3:$N$3,0)) -> 393.8 | D23: =INDEX(Data!$B$1:$N$20,MATCH($B23,Data!$B$1:$B$20,0),MATCH(D$5,Data!$B$3:$N$3,0)) -> 408.3 | E23: =INDEX(Data!$B$1:$N$20,MATCH($B23,Data!$B$1:$B$20,0),MATCH(E$5,Data!$B$3:$N$3,0)) -> 397.8 | F23: =INDEX(Data!$B$1:$N$20,MATCH($B23,Data!$B$1:$B$20,0),MATCH(F$5,Data!$B$3:$N$3,0)) -> 453.4 | G23: =SUM(C23:F23) -> 1653.3 | I23: =B23 -> Other expenses | J23: =SUM($C23:C23) -> 393.8 | K23: =SUM($C23:D23) -> 802.1 | L23: =SUM($C23:E23) -> 1199.9 | M23: =SUM($C23:F23) -> 1653.3
B24: Total | C24: =SUM(C20:C23) -> 2736.9 | D24: =SUM(D20:D23) -> 2603.3 | E24: =SUM(E20:E23) -> 2824.5 | F24: =SUM(F20:F23) -> 2576.2 | G24: =SUM(G20:G23) -> 10740.9 | I24: =B24 -> Total | J24: =SUM(J20:J23) -> 2736.9 | K24: =SUM(K20:K23) -> 5340.2 | L24: =SUM(L20:L23) -> 8164.7 | M24: =SUM(M20:M23) -> 10740.9

Sheet Budget vs Actuals
B2: Budget vs. Actuals by quarter
B4: Mar-26 | C4: ← Select quarter
B6: Selected quarter (₹ Cr) | I6: Year to Date
B7: Particulars | C7: Budget | D7: Actuals | E7: Variance | F7: Var % | G7: F / U | I7: Particulars | J7: YTD Budget | K7: YTD Actuals | L7: Variance | M7: Var % | N7: F / U
B8: Sales | C8: =INDEX(Budget!$C$19:$F$27,MATCH($B8,Budget!$B$19:$B$27,0),MATCH($B$4,Budget!$C$18:$F$18,0)) -> 2971.5 | D8: =INDEX(Actuals!$C$6:$F$14,MATCH($B8,Actuals!$B$6:$B$14,0),MATCH($B$4,Actuals!$C$5:$F$5,0)) -> 3038 | E8: =D8-C8 -> 66.5 | F8: =E8/C8 -> 0.02237927 | G8: =IF(ROUND(E8,4)=0,"-",IF(E8>0,"F","U")) -> F | I8: =$B8 -> Sales | J8: =INDEX(Budget!$J$19:$M$27,MATCH($I8,Budget!$I$19:$I$27,0),MATCH($B$4,Budget!$J$18:$M$18,0)) -> 13191.15 | K8: =INDEX(Actuals!$J$6:$M$14,MATCH($I8,Actuals!$I$6:$I$14,0),MATCH($B$4,Actuals!$J$5:$M$5,0)) -> 13193 | L8: =K8-J8 -> 1.85 | M8: =L8/J8 -> 0.00014024554 | N8: =IF(ROUND(L8,4)=0,"-",IF(L8>0,"F","U")) -> F
B9: Expenses | C9: =INDEX(Budget!$C$19:$F$27,MATCH($B9,Budget!$B$19:$B$27,0),MATCH($B$4,Budget!$C$18:$F$18,0)) -> 2523.465 | D9: =INDEX(Actuals!$C$6:$F$14,MATCH($B9,Actuals!$B$6:$B$14,0),MATCH($B$4,Actuals!$C$5:$F$5,0)) -> 2577 | E9: =C9-D9 -> -53.535 | F9: =E9/C9 -> -0.021214877 | G9: =IF(ROUND(E9,4)=0,"-",IF(E9>0,"F","U")) -> U | I9: =$B9 -> Expenses | J9: =INDEX(Budget!$J$19:$M$27,MATCH($I9,Budget!$I$19:$I$27,0),MATCH($B$4,Budget!$J$18:$M$18,0)) -> 10759.014 | K9: =INDEX(Actuals!$J$6:$M$14,MATCH($I9,Actuals!$I$6:$I$14,0),MATCH($B$4,Actuals!$J$5:$M$5,0)) -> 10742 | L9: =J9-K9 -> 17.014 | M9: =L9/J9 -> 0.0015813717 | N9: =IF(ROUND(L9,4)=0,"-",IF(L9>0,"F","U")) -> F
B10: Operating Profit | C10: =INDEX(Budget!$C$19:$F$27,MATCH($B10,Budget!$B$19:$B$27,0),MATCH($B$4,Budget!$C$18:$F$18,0)) -> 448.035 | D10: =INDEX(Actuals!$C$6:$F$14,MATCH($B10,Actuals!$B$6:$B$14,0),MATCH($B$4,Actuals!$C$5:$F$5,0)) -> 461 | E10: =D10-C10 -> 12.965 | F10: =E10/C10 -> 0.028937471 | G10: =IF(ROUND(E10,4)=0,"-",IF(E10>0,"F","U")) -> F | I10: =$B10 -> Operating Profit | J10: =INDEX(Budget!$J$19:$M$27,MATCH($I10,Budget!$I$19:$I$27,0),MATCH($B$4,Budget!$J$18:$M$18,0)) -> 2432.136 | K10: =INDEX(Actuals!$J$6:$M$14,MATCH($I10,Actuals!$I$6:$I$14,0),MATCH($B$4,Actuals!$J$5:$M$5,0)) -> 2450 | L10: =K10-J10 -> 17.864 | M10: =L10/J10 -> 0.007344984 | N10: =IF(ROUND(L10,4)=0,"-",IF(L10>0,"F","U")) -> F
B11: Other Income | C11: =INDEX(Budget!$C$19:$F$27,MATCH($B11,Budget!$B$19:$B$27,0),MATCH($B$4,Budget!$C$18:$F$18,0)) -> 148.05 | D11: =INDEX(Actuals!$C$6:$F$14,MATCH($B11,Actuals!$B$6:$B$14,0),MATCH($B$4,Actuals!$C$5:$F$5,0)) -> 175 | E11: =D11-C11 -> 26.95 | F11: =E11/C11 -> 0.1820331 | G11: =IF(ROUND(E11,4)=0,"-",IF(E11>0,"F","U")) -> F | I11: =$B11 -> Other Income | J11: =INDEX(Budget!$J$19:$M$27,MATCH($I11,Budget!$I$19:$I$27,0),MATCH($B$4,Budget!$J$18:$M$18,0)) -> 578.55 | K11: =INDEX(Actuals!$J$6:$M$14,MATCH($I11,Actuals!$I$6:$I$14,0),MATCH($B$4,Actuals!$J$5:$M$5,0)) -> 585 | L11: =K11-J11 -> 6.45 | M11: =L11/J11 -> 0.011148561 | N11: =IF(ROUND(L11,4)=0,"-",IF(L11>0,"F","U")) -> F
B12: Interest | C12: =INDEX(Budget!$C$19:$F$27,MATCH($B12,Budget!$B$19:$B$27,0),MATCH($B$4,Budget!$C$18:$F$18,0)) -> 39 | D12: =INDEX(Actuals!$C$6:$F$14,MATCH($B12,Actuals!$B$6:$B$14,0),MATCH($B$4,Actuals!$C$5:$F$5,0)) -> 40 | E12: =C12-D12 -> -1 | F12: =E12/C12 -> -0.025641026 | G12: =IF(ROUND(E12,4)=0,"-",IF(E12>0,"F","U")) -> U | I12: =$B12 -> Interest | J12: =INDEX(Budget!$J$19:$M$27,MATCH($I12,Budget!$I$19:$I$27,0),MATCH($B$4,Budget!$J$18:$M$18,0)) -> 163 | K12: =INDEX(Actuals!$J$6:$M$14,MATCH($I12,Actuals!$I$6:$I$14,0),MATCH($B$4,Actuals!$J$5:$M$5,0)) -> 146 | L12: =J12-K12 -> 17 | M12: =L12/J12 -> 0.10429448 | N12: =IF(ROUND(L12,4)=0,"-",IF(L12>0,"F","U")) -> F
B13: Depreciation | C13: =INDEX(Budget!$C$19:$F$27,MATCH($B13,Budget!$B$19:$B$27,0),MATCH($B$4,Budget!$C$18:$F$18,0)) -> 117 | D13: =INDEX(Actuals!$C$6:$F$14,MATCH($B13,Actuals!$B$6:$B$14,0),MATCH($B$4,Actuals!$C$5:$F$5,0)) -> 122 | E13: =C13-D13 -> -5 | F13: =E13/C13 -> -0.042735043 | G13: =IF(ROUND(E13,4)=0,"-",IF(E13>0,"F","U")) -> U | I13: =$B13 -> Depreciation | J13: =INDEX(Budget!$J$19:$M$27,MATCH($I13,Budget!$I$19:$I$27,0),MATCH($B$4,Budget!$J$18:$M$18,0)) -> 446 | K13: =INDEX(Actuals!$J$6:$M$14,MATCH($I13,Actuals!$I$6:$I$14,0),MATCH($B$4,Actuals!$J$5:$M$5,0)) -> 468 | L13: =J13-K13 -> -22 | M13: =L13/J13 -> -0.049327354 | N13: =IF(ROUND(L13,4)=0,"-",IF(L13>0,"F","U")) -> U
B14: Profit before tax | C14: =INDEX(Budget!$C$19:$F$27,MATCH($B14,Budget!$B$19:$B$27,0),MATCH($B$4,Budget!$C$18:$F$18,0)) -> 440.085 | D14: =INDEX(Actuals!$C$6:$F$14,MATCH($B14,Actuals!$B$6:$B$14,0),MATCH($B$4,Actuals!$C$5:$F$5,0)) -> 474 | E14: =D14-C14 -> 33.915 | F14: =E14/C14 -> 0.077064658 | G14: =IF(ROUND(E14,4)=0,"-",IF(E14>0,"F","U")) -> F | I14: =$B14 -> Profit before tax | J14: =INDEX(Budget!$J$19:$M$27,MATCH($I14,Budget!$I$19:$I$27,0),MATCH($B$4,Budget!$J$18:$M$18,0)) -> 2401.686 | K14: =INDEX(Actuals!$J$6:$M$14,MATCH($I14,Actuals!$I$6:$I$14,0),MATCH($B$4,Actuals!$J$5:$M$5,0)) -> 2421 | L14: =K14-J14 -> 19.314 | M14: =L14/J14 -> 0.0080418506 | N14: =IF(ROUND(L14,4)=0,"-",IF(L14>0,"F","U")) -> F
B15: Tax % | C15: =INDEX(Budget!$C$19:$F$27,MATCH($B15,Budget!$B$19:$B$27,0),MATCH($B$4,Budget!$C$18:$F$18,0)) -> 0.24 | D15: =INDEX(Actuals!$C$6:$F$14,MATCH($B15,Actuals!$B$6:$B$14,0),MATCH($B$4,Actuals!$C$5:$F$5,0)) -> 0.24 | E15: =C15-D15 -> 0 | G15: =IF(ROUND(E15,4)=0,"-",IF(E15>0,"F","U")) -> - | I15: =$B15 -> Tax % | J15: =INDEX(Budget!$J$19:$M$27,MATCH($I15,Budget!$I$19:$I$27,0),MATCH($B$4,Budget!$J$18:$M$18,0)) -> 0.23134947 | K15: =INDEX(Actuals!$J$6:$M$14,MATCH($I15,Actuals!$I$6:$I$14,0),MATCH($B$4,Actuals!$J$5:$M$5,0)) -> 0.22800496 | L15: =J15-K15 -> 0.003344512 | N15: =IF(ROUND(L15,4)=0,"-",IF(L15>0,"F","U")) -> F
B16: Net Profit | C16: =INDEX(Budget!$C$19:$F$27,MATCH($B16,Budget!$B$19:$B$27,0),MATCH($B$4,Budget!$C$18:$F$18,0)) -> 334.4646 | D16: =INDEX(Actuals!$C$6:$F$14,MATCH($B16,Actuals!$B$6:$B$14,0),MATCH($B$4,Actuals!$C$5:$F$5,0)) -> 362 | E16: =D16-C16 -> 27.5354 | F16: =E16/C16 -> 0.082326799 | G16: =IF(ROUND(E16,4)=0,"-",IF(E16>0,"F","U")) -> F | I16: =$B16 -> Net Profit | J16: =INDEX(Budget!$J$19:$M$27,MATCH($I16,Budget!$I$19:$I$27,0),MATCH($B$4,Budget!$J$18:$M$18,0)) -> 1846.0572 | K16: =INDEX(Actuals!$J$6:$M$14,MATCH($I16,Actuals!$I$6:$I$14,0),MATCH($B$4,Actuals!$J$5:$M$5,0)) -> 1869 | L16: =K16-J16 -> 22.94278 | M16: =L16/J16 -> 0.01242799 | N16: =IF(ROUND(L16,4)=0,"-",IF(L16>0,"F","U")) -> F
B18: Cost breakdown
B19: Cost line | C19: Budget | D19: Actuals | E19: Variance | F19: Var % | G19: F / U | I19: Cost line | J19: YTD Budget | K19: YTD Actuals | L19: Variance | M19: Var % | N19: F / U
B20: Material cost | C20: =INDEX(Budget!$C$33:$F$36,MATCH($B20,Budget!$B$33:$B$36,0),MATCH($B$4,Budget!$C$18:$F$18,0)) -> 1584.555 | D20: =INDEX(Actuals!$C$20:$F$23,MATCH($B20,Actuals!$B$20:$B$23,0),MATCH($B$4,Actuals!$C$5:$F$5,0)) -> 1570.1 | E20: =C20-D20 -> 14.455 | F20: =IF(C20=0,0,E20/C20) -> 0.009122435 | G20: =IF(ROUND(E20,4)=0,"-",IF(E20>0,"F","U")) -> F | I20: =$B20 -> Material cost | J20: =INDEX(Budget!$J$33:$M$36,MATCH($I20,Budget!$I$33:$I$36,0),MATCH($B$4,Budget!$J$18:$M$18,0)) -> 6861.5925 | K20: =INDEX(Actuals!$J$20:$M$23,MATCH($I20,Actuals!$I$20:$I$23,0),MATCH($B$4,Actuals!$J$5:$M$5,0)) -> 6823.8 | L20: =J20-K20 -> 37.7925 | M20: =IF(J20=0,0,L20/J20) -> 0.0055078322 | N20: =IF(ROUND(L20,4)=0,"-",IF(L20>0,"F","U")) -> F
B21: Employee cost | C21: =INDEX(Budget!$C$33:$F$36,MATCH($B21,Budget!$B$33:$B$36,0),MATCH($B$4,Budget!$C$18:$F$18,0)) -> 309.12 | D21: =INDEX(Actuals!$C$20:$F$23,MATCH($B21,Actuals!$B$20:$B$23,0),MATCH($B$4,Actuals!$C$5:$F$5,0)) -> 338.2 | E21: =C21-D21 -> -29.08 | F21: =IF(C21=0,0,E21/C21) -> -0.094073499 | G21: =IF(ROUND(E21,4)=0,"-",IF(E21>0,"F","U")) -> U | I21: =$B21 -> Employee cost | J21: =INDEX(Budget!$J$33:$M$36,MATCH($I21,Budget!$I$33:$I$36,0),MATCH($B$4,Budget!$J$18:$M$18,0)) -> 1355.886 | K21: =INDEX(Actuals!$J$20:$M$23,MATCH($I21,Actuals!$I$20:$I$23,0),MATCH($B$4,Actuals!$J$5:$M$5,0)) -> 1375.7 | L21: =J21-K21 -> -19.814 | M21: =IF(J21=0,0,L21/J21) -> -0.014613323 | N21: =IF(ROUND(L21,4)=0,"-",IF(L21>0,"F","U")) -> U
B22: Advertisement & publicity | C22: =INDEX(Budget!$C$33:$F$36,MATCH($B22,Budget!$B$33:$B$36,0),MATCH($B$4,Budget!$C$18:$F$18,0)) -> 185.22 | D22: =INDEX(Actuals!$C$20:$F$23,MATCH($B22,Actuals!$B$20:$B$23,0),MATCH($B$4,Actuals!$C$5:$F$5,0)) -> 214.5 | E22: =C22-D22 -> -29.28 | F22: =IF(C22=0,0,E22/C22) -> -0.15808228 | G22: =IF(ROUND(E22,4)=0,"-",IF(E22>0,"F","U")) -> U | I22: =$B22 -> Advertisement & publicity | J22: =INDEX(Budget!$J$33:$M$36,MATCH($I22,Budget!$I$33:$I$36,0),MATCH($B$4,Budget!$J$18:$M$18,0)) -> 907.8195 | K22: =INDEX(Actuals!$J$20:$M$23,MATCH($I22,Actuals!$I$20:$I$23,0),MATCH($B$4,Actuals!$J$5:$M$5,0)) -> 888.1 | L22: =J22-K22 -> 19.7195 | M22: =IF(J22=0,0,L22/J22) -> 0.021721829 | N22: =IF(ROUND(L22,4)=0,"-",IF(L22>0,"F","U")) -> F
B23: Other expenses | C23: =INDEX(Budget!$C$33:$F$36,MATCH($B23,Budget!$B$33:$B$36,0),MATCH($B$4,Budget!$C$18:$F$18,0)) -> 444.57 | D23: =INDEX(Actuals!$C$20:$F$23,MATCH($B23,Actuals!$B$20:$B$23,0),MATCH($B$4,Actuals!$C$5:$F$5,0)) -> 453.4 | E23: =C23-D23 -> -8.83 | F23: =IF(C23=0,0,E23/C23) -> -0.019861889 | G23: =IF(ROUND(E23,4)=0,"-",IF(E23>0,"F","U")) -> U | I23: =$B23 -> Other expenses | J23: =INDEX(Budget!$J$33:$M$36,MATCH($I23,Budget!$I$33:$I$36,0),MATCH($B$4,Budget!$J$18:$M$18,0)) -> 1633.716 | K23: =INDEX(Actuals!$J$20:$M$23,MATCH($I23,Actuals!$I$20:$I$23,0),MATCH($B$4,Actuals!$J$5:$M$5,0)) -> 1653.3 | L23: =J23-K23 -> -19.584 | M23: =IF(J23=0,0,L23/J23) -> -0.011987396 | N23: =IF(ROUND(L23,4)=0,"-",IF(L23>0,"F","U")) -> U
B25: Key variances by quarter - commentary
B26: Quarter | C26: Line item | D26: Variance | E26: F / U | F26: What happened and why | O26: Source
B27: Jun-25 | C27: Sales | D27: =IF(OR(C27="Expenses",C27="Interest",C27="Depreciation"),1,-1)*(INDEX(Budget!$C$19:$F$27,MATCH(C27,Budget!$B$19:$B$27,0),MATCH(B27,Budget!$C$18:$F$18,0))-INDEX(Actuals!$C$6:$F$14,MATCH(C27,Actuals!$B$6:$B$14,0),MATCH(B27,Actuals!$C$5:$F$5,0))) -> -111.45 | E27: =IF(ROUND(D27,4)=0,"-",IF(D27>0,"F","U")) -> U | F27: Unseasonal summer rains hurt drinks and other summer products. Sales came in ₹111 Cr below budget. | O27: Dabur Q1 FY26 results and earnings call
B28: Jun-25 | C28: Expenses | D28: =IF(OR(C28="Expenses",C28="Interest",C28="Depreciation"),1,-1)*(INDEX(Budget!$C$19:$F$27,MATCH(C28,Budget!$B$19:$B$27,0),MATCH(B28,Budget!$C$18:$F$18,0))-INDEX(Actuals!$C$6:$F$14,MATCH(C28,Actuals!$B$6:$B$14,0),MATCH(B28,Actuals!$C$5:$F$5,0))) -> 91.784 | E28: =IF(ROUND(D28,4)=0,"-",IF(D28>0,"F","U")) -> F | F28: Costs fell in line with lower sales (both about 3% below budget). Ad spend was also cut 14% to ₹202 Cr. | O28: Dabur Q1 FY26 results
B29: Jun-25 | C29: Operating Profit | D29: =IF(OR(C29="Expenses",C29="Interest",C29="Depreciation"),1,-1)*(INDEX(Budget!$C$19:$F$27,MATCH(C29,Budget!$B$19:$B$27,0),MATCH(B29,Budget!$C$18:$F$18,0))-INDEX(Actuals!$C$6:$F$14,MATCH(C29,Actuals!$B$6:$B$14,0),MATCH(B29,Actuals!$C$5:$F$5,0))) -> -20.666 | E29: =IF(ROUND(D29,4)=0,"-",IF(D29>0,"F","U")) -> U | F29: Operating profit was ₹667 Cr vs ₹688 Cr budget. Margin held at about 19.6%, so the miss came from lower sales, not higher costs. | O29: Model calculation (Budget and Actuals sheets)
B30: Sep-25 | C30: Sales | D30: =IF(OR(C30="Expenses",C30="Interest",C30="Depreciation"),1,-1)*(INDEX(Budget!$C$19:$F$27,MATCH(C30,Budget!$B$19:$B$27,0),MATCH(B30,Budget!$C$18:$F$18,0))-INDEX(Actuals!$C$6:$F$14,MATCH(C30,Actuals!$B$6:$B$14,0),MATCH(B30,Actuals!$C$5:$F$5,0))) -> 10.55 | E30: =IF(ROUND(D30,4)=0,"-",IF(D30>0,"F","U")) -> F | F30: Sales grew 5.4% to ₹3,191 Cr, slightly above budget. The GST rate cut made distributors cut stock (about ₹100 Cr hit) and heavy rains hurt juices, but toothpaste, foods and juices gained market share. | O30: Dabur Q2 FY26 investor communication and earnings call
B31: Sep-25 | C31: Expenses | D31: =IF(OR(C31="Expenses",C31="Interest",C31="Depreciation"),1,-1)*(INDEX(Budget!$C$19:$F$27,MATCH(C31,Budget!$B$19:$B$27,0),MATCH(B31,Budget!$C$18:$F$18,0))-INDEX(Actuals!$C$6:$F$14,MATCH(C31,Actuals!$B$6:$B$14,0),MATCH(B31,Actuals!$C$5:$F$5,0))) -> -3.2 | E31: =IF(ROUND(D31,4)=0,"-",IF(D31>0,"F","U")) -> U | F31: Costs were in line with budget. Raw material costs rose about 8%, but price increases and cost savings made up for it. | O31: Dabur Q2 FY26 investor communication
B32: Sep-25 | C32: Net Profit | D32: =IF(OR(C32="Expenses",C32="Interest",C32="Depreciation"),1,-1)*(INDEX(Budget!$C$19:$F$27,MATCH(C32,Budget!$B$19:$B$27,0),MATCH(B32,Budget!$C$18:$F$18,0))-INDEX(Actuals!$C$6:$F$14,MATCH(C32,Actuals!$B$6:$B$14,0),MATCH(B32,Actuals!$C$5:$F$5,0))) -> 2.49 | E32: =IF(ROUND(D32,4)=0,"-",IF(D32>0,"F","U")) -> F | F32: Net profit was ₹445 Cr, slightly above budget, helped by lower interest and a lower tax rate. The company reports ₹453 Cr because it uses profit after minority interest. | O32: Dabur Q2 FY26 investor communication
B33: Dec-25 | C33: Sales | D33: =IF(OR(C33="Expenses",C33="Interest",C33="Depreciation"),1,-1)*(INDEX(Budget!$C$19:$F$27,MATCH(C33,Budget!$B$19:$B$27,0),MATCH(B33,Budget!$C$18:$F$18,0))-INDEX(Actuals!$C$6:$F$14,MATCH(C33,Actuals!$B$6:$B$14,0),MATCH(B33,Actuals!$C$5:$F$5,0))) -> 36.25 | E33: =IF(ROUND(D33,4)=0,"-",IF(D33>0,"F","U")) -> F | F33: Sales grew 6.1% to ₹3,559 Cr, above budget. October was slow after the GST cut, but demand recovered in November and December. Hair oils (+19%), toothpaste, foods and rural sales led growth. | O33: Dabur Q3 FY26 investor communication and earnings call
B34: Dec-25 | C34: Operating Profit | D34: =IF(OR(C34="Expenses",C34="Interest",C34="Depreciation"),1,-1)*(INDEX(Budget!$C$19:$F$27,MATCH(C34,Budget!$B$19:$B$27,0),MATCH(B34,Budget!$C$18:$F$18,0))-INDEX(Actuals!$C$6:$F$14,MATCH(C34,Actuals!$B$6:$B$14,0),MATCH(B34,Actuals!$C$5:$F$5,0))) -> 18.215 | E34: =IF(ROUND(D34,4)=0,"-",IF(D34>0,"F","U")) -> F | F34: Operating profit grew 7.7% to ₹734 Cr and margin rose to 20.6%. Coconut oil prices roughly doubled, but price increases and cost savings covered it. | O34: Dabur Q3 FY26 investor communication and earnings call
B35: Dec-25 | C35: Interest | D35: =IF(OR(C35="Expenses",C35="Interest",C35="Depreciation"),1,-1)*(INDEX(Budget!$C$19:$F$27,MATCH(C35,Budget!$B$19:$B$27,0),MATCH(B35,Budget!$C$18:$F$18,0))-INDEX(Actuals!$C$6:$F$14,MATCH(C35,Actuals!$B$6:$B$14,0),MATCH(B35,Actuals!$C$5:$F$5,0))) -> 13 | E35: =IF(ROUND(D35,4)=0,"-",IF(D35>0,"F","U")) -> F | F35: Interest was ₹31 Cr vs ₹44 Cr budget (₹13 Cr saving). This is likely due to lower borrowings, as the budget used last year's higher interest cost. To be confirmed from the debt schedule. | O35: Dabur Q3 FY26 investor communication; FY25 annual report
B36: Mar-26 | C36: Sales | D36: =IF(OR(C36="Expenses",C36="Interest",C36="Depreciation"),1,-1)*(INDEX(Budget!$C$19:$F$27,MATCH(C36,Budget!$B$19:$B$27,0),MATCH(B36,Budget!$C$18:$F$18,0))-INDEX(Actuals!$C$6:$F$14,MATCH(C36,Actuals!$B$6:$B$14,0),MATCH(B36,Actuals!$C$5:$F$5,0))) -> 66.5 | E36: =IF(ROUND(D36,4)=0,"-",IF(D36>0,"F","U")) -> F | F36: Sales grew 7.3% to ₹3,038 Cr, above budget. Hair oils, shampoo, home care and foods grew strongly, helped by fast growth in online sales. International sales were weak due to the Middle East conflict. | O36: Dabur Q4 FY26 investor communication and earnings call
B37: Mar-26 | C37: Expenses | D37: =IF(OR(C37="Expenses",C37="Interest",C37="Depreciation"),1,-1)*(INDEX(Budget!$C$19:$F$27,MATCH(C37,Budget!$B$19:$B$27,0),MATCH(B37,Budget!$C$18:$F$18,0))-INDEX(Actuals!$C$6:$F$14,MATCH(C37,Actuals!$B$6:$B$14,0),MATCH(B37,Actuals!$C$5:$F$5,0))) -> -53.535 | E37: =IF(ROUND(D37,4)=0,"-",IF(D37>0,"F","U")) -> U | F37: Costs were about ₹54 Cr over budget, mainly from higher ad spend (₹29 Cr over) and staff costs (₹29 Cr over). Material costs were ₹15 Cr under budget. Management expects about 10% cost inflation next year and has raised prices by about 4%. | O37: Dabur Q4 FY26 investor communication and earnings call
B38: Mar-26 | C38: Net Profit | D38: =IF(OR(C38="Expenses",C38="Interest",C38="Depreciation"),1,-1)*(INDEX(Budget!$C$19:$F$27,MATCH(C38,Budget!$B$19:$B$27,0),MATCH(B38,Budget!$C$18:$F$18,0))-INDEX(Actuals!$C$6:$F$14,MATCH(C38,Actuals!$B$6:$B$14,0),MATCH(B38,Actuals!$C$5:$F$5,0))) -> 27.5354 | E38: =IF(ROUND(D38,4)=0,"-",IF(D38>0,"F","U")) -> F | F38: Net profit rose 16% to ₹362 Cr, above budget. Operating profit grew faster than sales, and other income was higher (about ₹175 Cr vs ₹141 Cr last year). | O38: Dabur Q4 FY26 investor communication

Sheet Variance Drivers
B2: Variance drivers
B4: Cost ratios: Budget vs actual (% of sales)
B5: Cost line | C5: Budget % of sales | D5: Actual % of sales | E5: Change (pts) | F5: F / U
B6: Material cost | C6: =Budget!G33/Budget!$G$19 -> 0.52016636 | D6: =Actuals!G20/Actuals!$G$6 -> 0.51722883 | E6: =(C6-D6)*100 -> 0.29375281 | F6: =IF(ROUND(E6,4)=0,"-",IF(E6>0,"F","U")) -> F
B7: Employee cost | C7: =Budget!G34/Budget!$G$19 -> 0.10278755 | D7: =Actuals!G21/Actuals!$G$6 -> 0.10427499 | E7: =(C7-D7)*100 -> -0.14874436 | F7: =IF(ROUND(E7,4)=0,"-",IF(E7>0,"F","U")) -> U
B8: Advertisement & publicity | C8: =Budget!G35/Budget!$G$19 -> 0.068820345 | D8: =Actuals!G22/Actuals!$G$6 -> 0.067316001 | E8: =(C8-D8)*100 -> 0.15043445 | F8: =IF(ROUND(E8,4)=0,"-",IF(E8>0,"F","U")) -> F
B9: Other expenses | C9: =Budget!G36/Budget!$G$19 -> 0.1238494 | D9: =Actuals!G23/Actuals!$G$6 -> 0.12531646 | E9: =(C9-D9)*100 -> -0.14670567 | F9: =IF(ROUND(E9,4)=0,"-",IF(E9>0,"F","U")) -> U
B10: Total | C10: =SUM(C6:C9) -> 0.81562366 | D10: =SUM(D6:D9) -> 0.81413628 | E10: =(C10-D10)*100 -> 0.14873724 | F10: =IF(ROUND(E10,4)=0,"-",IF(E10>0,"F","U")) -> F
B12: Sales variance: volume vs price/mix (₹ Cr)
B13: ₹ Cr | C13: Jun-25 | D13: Sep-25 | E13: Dec-25 | F13: Mar-26 | G13: FY26
B14: Prior-year sales (FY25, same quarter) | C14: =Budget!C6 -> 3349 | D14: =Budget!D6 -> 3029 | E14: =Budget!E6 -> 3355 | F14: =Budget!F6 -> 2830 | G14: =SUM(C14:F14) -> 12563
B15: Budget volume growth | C15: =Budget!$C$44 -> 0.03 | D15: =Budget!$C$44 -> 0.03 | E15: =Budget!$C$44 -> 0.03 | F15: =Budget!$C$44 -> 0.03 | G15: =C15 -> 0.03
B16: Budget price/mix growth | C16: =Budget!$C$45 -> 0.019417476 | D16: =Budget!$C$45 -> 0.019417476 | E16: =Budget!$C$45 -> 0.019417476 | F16: =Budget!$C$45 -> 0.019417476 | G16: =C16 -> 0.019417476
B17: Actual volume growth (India FMCG, proxy) | C17: =Data!K22 -> -0.01 | D17: =Data!L22 -> 0.02 | E17: =Data!M22 -> 0.03 | F17: =Data!N22 -> 0.06
B18: Actual price/mix growth (implied) | C18: =(C21/C14)/(1+C17)-1 -> 0.026991323 | D18: =(D21/D14)/(1+D17)-1 -> 0.032826468 | E18: =(E21/E14)/(1+E17)-1 -> 0.029907543 | F18: =(F21/F14)/(1+F17)-1 -> 0.012734182
B19: Step 1: Budget sales (budget volume, budget price) | C19: =Budget!C19 -> 3516.45 | D19: =Budget!D19 -> 3180.45 | E19: =Budget!E19 -> 3522.75 | F19: =Budget!F19 -> 2971.5 | G19: =SUM(C19:F19) -> 13191.15
B20: Step 2: Sales at actual volume, budget price | C20: =C14*(1+C17)*(1+C16) -> 3379.8888 | D20: =D14*(1+D17)*(1+D16) -> 3149.5718 | E20: =E14*(1+E17)*(1+E16) -> 3522.75 | F20: =F14*(1+F17)*(1+F16) -> 3058.0485 | G20: =SUM(C20:F20) -> 13110.259
B21: Step 3: Actual sales (actual volume, actual price) | C21: =Actuals!C6 -> 3405 | D21: =Actuals!D6 -> 3191 | E21: =Actuals!E6 -> 3559 | F21: =Actuals!F6 -> 3038 | G21: =SUM(C21:F21) -> 13193
B22: Volume variance | C22: =C20-C19 -> -136.56117 | D22: =D20-D19 -> -30.878155 | E22: =E20-E19 -> 0 | F22: =F20-F19 -> 86.548544 | G22: =SUM(C22:F22) -> -80.890777
B23: Price/mix variance | C23: =C21-C20 -> 25.111165 | D23: =D21-D20 -> 41.428155 | E23: =E21-E20 -> 36.25 | F23: =F21-F20 -> -20.048544 | G23: =SUM(C23:F23) -> 82.740777
B24: Total sales variance | C24: =C22+C23 -> -111.45 | D24: =D22+D23 -> 10.55 | E24: =E22+E23 -> 36.25 | F24: =F22+F23 -> 66.5 | G24: =SUM(C24:F24) -> 1.85
B25: Check: total (actual minus budget sales) | C25: =ROUND(C24-(C21-C19),6) -> 0 | D25: =ROUND(D24-(D21-D19),6) -> 0 | E25: =ROUND(E24-(E21-E19),6) -> 0 | F25: =ROUND(F24-(F21-F19),6) -> 0 | G25: =ROUND(G24-(G21-G19),6) -> 0
B27: 3. Net profit bridge: FY26 budget to actual (₹ Cr)
B28: Step | C28: Impact
B29: Budget net profit | C29: =Budget!G27 -> 1846.0572
B30: Sales: volume | C30: =G22 -> -80.890777
B31: Sales: price/mix | C31: =G23 -> 82.740777
B32: Material cost | C32: =Budget!G33-Actuals!G20 -> 37.7925
B33: Employee cost | C33: =Budget!G34-Actuals!G21 -> -19.814
B34: Advertisement & publicity | C34: =Budget!G35-Actuals!G22 -> 19.7195
B35: Other expenses & rounding | C35: =(Actuals!G8-Budget!G21)-SUM(C30:C34) -> -21.684
B36: Other income | C36: =Actuals!G9-Budget!G22 -> 6.45
B37: Interest | C37: =Budget!G23-Actuals!G10 -> 17
B38: Depreciation | C38: =Budget!G24-Actuals!G11 -> -22
B39: Tax & minority | C39: =(Budget!G25-Budget!G27)-(Actuals!G12-Actuals!G14) -> 3.62878
B40: Actual net profit | C40: =Actuals!G14 -> 1869

Sheet Data
B1: Dabur India - Quarterly Results (Consolidated, ₹ Cr)
B3: ₹ Cr | C3: Jun-23 | D3: Sep-23 | E3: Dec-23 | F3: Mar-24 | G3: Jun-24 | H3: Sep-24 | I3: Dec-24 | J3: Mar-25 | K3: Jun-25 | L3: Sep-25 | M3: Dec-25 | N3: Mar-26
B4: Sales | C4: 3130 | D4: 3204 | E4: 3255 | F4: 2815 | G4: 3349 | H4: 3029 | I4: 3355 | J4: 2830 | K4: 3405 | L4: 3191 | M4: 3559 | N4: 3038
B5: Expenses | C5: 2526 | D5: 2543 | E5: 2588 | F5: 2348 | G5: 2694 | H5: 2476 | I5: 2673 | J5: 2403 | K5: 2737 | L5: 2603 | M5: 2825 | N5: 2577
B6: Operating Profit | C6: 605 | D6: 661 | E6: 667 | F6: 466 | G6: 655 | H6: 553 | I6: 682 | J6: 427 | K6: 667 | L6: 588 | M6: 734 | N6: 461
B7: OPM % | C7: 0.19 | D7: 0.21 | E7: 0.2 | F7: 0.17 | G7: 0.2 | H7: 0.18 | I7: 0.2 | J7: 0.15 | K7: 0.2 | L7: 0.18 | M7: 0.21 | N7: 0.15
B8: Other Income | C8: 110 | D8: 117 | E8: 127 | F8: 129 | G8: 129 | H8: 152 | I8: 129 | J8: 141 | K8: 144 | L8: 140 | M8: 126 | N8: 175
B9: Interest | C9: 24 | D9: 28 | E9: 36 | F9: 35 | G9: 33 | H9: 47 | I9: 44 | J9: 39 | K9: 35 | L9: 40 | M9: 31 | N9: 40
B10: Depreciation | C10: 97 | D10: 98 | E10: 97 | F10: 107 | G10: 109 | H10: 111 | I10: 109 | J10: 117 | K10: 114 | L10: 115 | M10: 117 | N10: 122
B11: Profit before tax | C11: 593 | D11: 651 | E11: 661 | F11: 453 | G11: 642 | H11: 546 | I11: 658 | J11: 412 | K11: 663 | L11: 573 | M11: 711 | N11: 474
B12: Tax % | C12: 0.23 | D12: 0.22 | E12: 0.23 | F12: 0.25 | G12: 0.23 | H12: 0.24 | I12: 0.22 | J12: 0.24 | K12: 0.23 | L12: 0.22 | M12: 0.22 | N12: 0.24
B13: Net Profit | C13: 457 | D13: 507 | E13: 506 | F13: 341 | G13: 494 | H13: 418 | I13: 516 | J13: 313 | K13: 508 | L13: 445 | M13: 554 | N13: 362
B15: Cost breakdown (₹ Cr) - from Dabur results filings
B16: Material cost | G16: 1748.65 | H16: 1534.3 | I16: 1742.8 | J16: 1509.1 | K16: 1803.3 | L16: 1613.5 | M16: 1836.9 | N16: 1570.1
B17: Employee cost | G17: 322.92 | H17: 338.8 | I17: 335.2 | J17: 294.4 | K17: 337.8 | L17: 347.9 | M17: 351.8 | N17: 338.2
B18: Advertisement & publicity | G18: 235.89 | H18: 225.6 | I18: 226.7 | J18: 176.4 | K18: 202 | L18: 233.6 | M18: 238 | N18: 214.5
B19: Other expenses | G19: 386.62 | H19: 377.3 | I19: 368.6 | J19: 423.4 | K19: 393.8 | L19: 408.3 | M19: 397.8 | N19: 453.4
B20: Total of line items | G20: =SUM(G16:G19) -> 2694.08 | H20: =SUM(H16:H19) -> 2476 | I20: =SUM(I16:I19) -> 2673.3 | J20: =SUM(J16:J19) -> 2403.3 | K20: =SUM(K16:K19) -> 2736.9 | L20: =SUM(L16:L19) -> 2603.3 | M20: =SUM(M16:M19) -> 2824.5 | N20: =SUM(N16:N19) -> 2576.2
B22: India FMCG volume growth (YoY) | K22: -0.01 | L22: 0.02 | M22: 0.03 | N22: 0.06
B24: Volume growth is for the India FMCG business only (about two-thirds of sales). It is used as a proxy for the whole group in the volume vs price/mix split.
B26: Analysis rows
B27: Sales growth YoY | G27: =G4/C4-1 -> 0.069968051 | H27: =H4/D4-1 -> -0.054619226 | I27: =I4/E4-1 -> 0.030721966 | J27: =J4/F4-1 -> 0.0053285968 | K27: =K4/G4-1 -> 0.016721409 | L27: =L4/H4-1 -> 0.053482998 | M27: =M4/I4-1 -> 0.060804769 | N27: =N4/J4-1 -> 0.073498233
B28: Expenses % of sales | C28: =C5/C4 -> 0.80702875 | D28: =D5/D4 -> 0.79369538 | E28: =E5/E4 -> 0.79508449 | F28: =F5/F4 -> 0.83410302 | G28: =G5/G4 -> 0.80441923 | H28: =H5/H4 -> 0.8174315 | I28: =I5/I4 -> 0.79672131 | J28: =J5/J4 -> 0.84911661 | ... N28: =N5/N4 -> 0.84825543
B31: Fiscal year totals
B32: Particulars | C32: FY24 (Jun-23 to Mar-24) | D32: FY25 (Jun-24 to Mar-25) | E32: FY26 (Jun-25 to Mar-26)
B33: Sales | C33: =SUM(C4:F4) -> 12404 | D33: =SUM(G4:J4) -> 12563 | E33: =SUM(K4:N4) -> 13193
B34: Sales Growth | D34: =D33/C33-1 -> 0.012818446 | E34: =E33/D33-1 -> 0.050147258
